{
  "id": "1f74f79d-40cf-43b5-a0af-2e962541d315",
  "prevId": "6ca7bc7d-fb92-4568-85c4-43fda1232972",
  "version": "7",
  "dialect": "postgresql",
  "tables": {
    "public.sandbox_secrets": {
      "name": "sandbox_secrets",
      "schema": "",
      "columns": {
        "id": {
          "name": "id",
          "type": "text",
          "primaryKey": true,
          "notNull": true,
          "default": "xata_id()"
        },
        "sandbox_id": {
          "name": "sandbox_id",
          "type": "text",
          "primaryKey": false,
          "notNull": true
        },
        "secret_id": {
          "name": "secret_id",
          "type": "text",
          "primaryKey": false,
          "notNull": true
        }
      },
      "indexes": {
        "unique_sandbox_secret": {
          "name": "unique_sandbox_secret",
          "columns": [
            {
              "expression": "sandbox_id",
              "isExpression": false,
              "asc": true,
              "nulls": "last"
            },
            {
              "expression": "secret_id",
              "isExpression": false,
              "asc": true,
              "nulls": "last"
            }
          ],
          "isUnique": true,
          "concurrently": false,
          "method": "btree",
          "with": {}
        }
      },
      "foreignKeys": {
        "sandbox_secrets_sandbox_id_sandboxes_id_fk": {
          "name": "sandbox_secrets_sandbox_id_sandboxes_id_fk",
          "tableFrom": "sandbox_secrets",
          "tableTo": "sandboxes",
          "columnsFrom": [
            "sandbox_id"
          ],
          "columnsTo": [
            "id"
          ],
          "onDelete": "no action",
          "onUpdate": "no action"
        },
        "sandbox_secrets_secret_id_secrets_id_fk": {
          "name": "sandbox_secrets_secret_id_secrets_id_fk",
          "tableFrom": "sandbox_secrets",
          "tableTo": "secrets",
          "columnsFrom": [
            "secret_id"
          ],
          "columnsTo": [
            "id"
          ],
          "onDelete": "no action",
          "onUpdate": "no action"
        }
      },
      "compositePrimaryKeys": {},
      "uniqueConstraints": {},
      "policies": {},
      "checkConstraints": {},
      "isRLSEnabled": false
    },
    "public.sandbox_variables": {
      "name": "sandbox_variables",
      "schema": "",
      "columns": {
        "id": {
          "name": "id",
          "type": "text",
          "primaryKey": true,
          "notNull": true,
          "default": "xata_id()"
        },
        "sandbox_id": {
          "name": "sandbox_id",
          "type": "text",
          "primaryKey": false,
          "notNull": true
        },
        "variable_id": {
          "name": "variable_id",
          "type": "text",
          "primaryKey": false,
          "notNull": true
        }
      },
      "indexes": {
        "unique_sandbox_variables": {
          "name": "unique_sandbox_variables",
          "columns": [
            {
              "expression": "sandbox_id",
              "isExpression": false,
              "asc": true,
              "nulls": "last"
            },
            {
              "expression": "variable_id",
              "isExpression": false,
              "asc": true,
              "nulls": "last"
            }
          ],
          "isUnique": true,
          "concurrently": false,
          "method": "btree",
          "with": {}
        }
      },
      "foreignKeys": {
        "sandbox_variables_sandbox_id_sandboxes_id_fk": {
          "name": "sandbox_variables_sandbox_id_sandboxes_id_fk",
          "tableFrom": "sandbox_variables",
          "tableTo": "sandboxes",
          "columnsFrom": [
            "sandbox_id"
          ],
          "columnsTo": [
            "id"
          ],
          "onDelete": "no action",
          "onUpdate": "no action"
        },
        "sandbox_variables_variable_id_variables_id_fk": {
          "name": "sandbox_variables_variable_id_variables_id_fk",
          "tableFrom": "sandbox_variables",
          "tableTo": "variables",
          "columnsFrom": [
            "variable_id"
          ],
          "columnsTo": [
            "id"
          ],
          "onDelete": "no action",
          "onUpdate": "no action"
        }
      },
      "compositePrimaryKeys": {},
      "uniqueConstraints": {},
      "policies": {},
      "checkConstraints": {},
      "isRLSEnabled": false
    },
    "public.sandbox_volumes": {
      "name": "sandbox_volumes",
      "schema": "",
      "columns": {
        "id": {
          "name": "id",
          "type": "text",
          "primaryKey": true,
          "notNull": true,
          "default": "xata_id()"
        },
        "sandbox_id": {
          "name": "sandbox_id",
          "type": "text",
          "primaryKey": false,
          "notNull": true
        },
        "volume_id": {
          "name": "volume_id",
          "type": "text",
          "primaryKey": false,
          "notNull": true
        }
      },
      "indexes": {},
      "foreignKeys": {
        "sandbox_volumes_sandbox_id_sandboxes_id_fk": {
          "name": "sandbox_volumes_sandbox_id_sandboxes_id_fk",
          "tableFrom": "sandbox_volumes",
          "tableTo": "sandboxes",
          "columnsFrom": [
            "sandbox_id"
          ],
          "columnsTo": [
            "id"
          ],
          "onDelete": "no action",
          "onUpdate": "no action"
        },
        "sandbox_volumes_volume_id_volumes_id_fk": {
          "name": "sandbox_volumes_volume_id_volumes_id_fk",
          "tableFrom": "sandbox_volumes",
          "tableTo": "volumes",
          "columnsFrom": [
            "volume_id"
          ],
          "columnsTo": [
            "id"
          ],
          "onDelete": "no action",
          "onUpdate": "no action"
        }
      },
      "compositePrimaryKeys": {},
      "uniqueConstraints": {},
      "policies": {},
      "checkConstraints": {},
      "isRLSEnabled": false
    },
    "public.sandboxes": {
      "name": "sandboxes",
      "schema": "",
      "columns": {
        "id": {
          "name": "id",
          "type": "text",
          "primaryKey": true,
          "notNull": true,
          "default": "sandbox_id()"
        },
        "base": {
          "name": "base",
          "type": "text",
          "primaryKey": false,
          "notNull": false
        },
        "name": {
          "name": "name",
          "type": "text",
          "primaryKey": false,
          "notNull": true
        },
        "display_name": {
          "name": "display_name",
          "type": "text",
          "primaryKey": false,
          "notNull": false
        },
        "uri": {
          "name": "uri",
          "type": "text",
          "primaryKey": false,
          "notNull": false
        },
        "provider": {
          "name": "provider",
          "type": "text",
          "primaryKey": false,
          "notNull": true,
          "default": "'cloudflare'"
        },
        "description": {
          "name": "description",
          "type": "text",
          "primaryKey": false,
          "notNull": false
        },
        "logo": {
          "name": "logo",
          "type": "text",
          "primaryKey": false,
          "notNull": false
        },
        "public_key": {
          "name": "public_key",
          "type": "text",
          "primaryKey": false,
          "notNull": true
        },
        "user_id": {
          "name": "user_id",
          "type": "text",
          "primaryKey": false,
          "notNull": false
        },
        "instance_type": {
          "name": "instance_type",
          "type": "text",
          "primaryKey": false,
          "notNull": false
        },
        "vcpus": {
          "name": "vcpus",
          "type": "integer",
          "primaryKey": false,
          "notNull": false
        },
        "memory": {
          "name": "memory",
          "type": "integer",
          "primaryKey": false,
          "notNull": false
        },
        "disk": {
          "name": "disk",
          "type": "integer",
          "primaryKey": false,
          "notNull": false
        },
        "status": {
          "name": "status",
          "type": "text",
          "primaryKey": false,
          "notNull": true
        },
        "keep_alive": {
          "name": "keep_alive",
          "type": "boolean",
          "primaryKey": false,
          "notNull": true,
          "default": false
        },
        "sleep_after": {
          "name": "sleep_after",
          "type": "text",
          "primaryKey": false,
          "notNull": false
        },
        "sandbox_id": {
          "name": "sandbox_id",
          "type": "text",
          "primaryKey": false,
          "notNull": false
        },
        "created_at": {
          "name": "created_at",
          "type": "timestamp",
          "primaryKey": false,
          "notNull": true,
          "default": "now()"
        },
        "updated_at": {
          "name": "updated_at",
          "type": "timestamp",
          "primaryKey": false,
          "notNull": true,
          "default": "now()"
        }
      },
      "indexes": {},
      "foreignKeys": {
        "sandboxes_user_id_users_id_fk": {
          "name": "sandboxes_user_id_users_id_fk",
          "tableFrom": "sandboxes",
          "tableTo": "users",
          "columnsFrom": [
            "user_id"
          ],
          "columnsTo": [
            "id"
          ],
          "onDelete": "no action",
          "onUpdate": "no action"
        }
      },
      "compositePrimaryKeys": {},
      "uniqueConstraints": {
        "sandboxes_name_unique": {
          "name": "sandboxes_name_unique",
          "nullsNotDistinct": false,
          "columns": [
            "name"
          ]
        },
        "sandboxes_uri_unique": {
          "name": "sandboxes_uri_unique",
          "nullsNotDistinct": false,
          "columns": [
            "uri"
          ]
        }
      },
      "policies": {},
      "checkConstraints": {},
      "isRLSEnabled": false
    },
    "public.secrets": {
      "name": "secrets",
      "schema": "",
      "columns": {
        "id": {
          "name": "id",
          "type": "text",
          "primaryKey": true,
          "notNull": true,
          "default": "secret_id()"
        },
        "name": {
          "name": "name",
          "type": "text",
          "primaryKey": false,
          "notNull": true
        },
        "value": {
          "name": "value",
          "type": "text",
          "primaryKey": false,
          "notNull": true
        },
        "created_at": {
          "name": "created_at",
          "type": "timestamp",
          "primaryKey": false,
          "notNull": true,
          "default": "now()"
        }
      },
      "indexes": {},
      "foreignKeys": {},
      "compositePrimaryKeys": {},
      "uniqueConstraints": {},
      "policies": {},
      "checkConstraints": {},
      "isRLSEnabled": false
    },
    "public.snapshots": {
      "name": "snapshots",
      "schema": "",
      "columns": {
        "id": {
          "name": "id",
          "type": "text",
          "primaryKey": true,
          "notNull": true,
          "default": "snapshot_id()"
        },
        "slug": {
          "name": "slug",
          "type": "text",
          "primaryKey": false,
          "notNull": true
        },
        "created_at": {
          "name": "created_at",
          "type": "timestamp",
          "primaryKey": false,
          "notNull": true,
          "default": "now()"
        }
      },
      "indexes": {},
      "foreignKeys": {},
      "compositePrimaryKeys": {},
      "uniqueConstraints": {
        "snapshots_slug_unique": {
          "name": "snapshots_slug_unique",
          "nullsNotDistinct": false,
          "columns": [
            "slug"
          ]
        }
      },
      "policies": {},
      "checkConstraints": {},
      "isRLSEnabled": false
    },
    "public.users": {
      "name": "users",
      "schema": "",
      "columns": {
        "id": {
          "name": "id",
          "type": "text",
          "primaryKey": true,
          "notNull": true,
          "default": "xata_id()"
        },
        "did": {
          "name": "did",
          "type": "text",
          "primaryKey": false,
          "notNull": true
        },
        "display_name": {
          "name": "display_name",
          "type": "text",
          "primaryKey": false,
          "notNull": false
        },
        "handle": {
          "name": "handle",
          "type": "text",
          "primaryKey": false,
          "notNull": true
        },
        "avatar": {
          "name": "avatar",
          "type": "text",
          "primaryKey": false,
          "notNull": false
        },
        "created_at": {
          "name": "created_at",
          "type": "timestamp",
          "primaryKey": false,
          "notNull": true,
          "default": "now()"
        },
        "updated_at": {
          "name": "updated_at",
          "type": "timestamp",
          "primaryKey": false,
          "notNull": true,
          "default": "now()"
        }
      },
      "indexes": {},
      "foreignKeys": {},
      "compositePrimaryKeys": {},
      "uniqueConstraints": {
        "users_did_unique": {
          "name": "users_did_unique",
          "nullsNotDistinct": false,
          "columns": [
            "did"
          ]
        },
        "users_handle_unique": {
          "name": "users_handle_unique",
          "nullsNotDistinct": false,
          "columns": [
            "handle"
          ]
        }
      },
      "policies": {},
      "checkConstraints": {},
      "isRLSEnabled": false
    },
    "public.variables": {
      "name": "variables",
      "schema": "",
      "columns": {
        "id": {
          "name": "id",
          "type": "text",
          "primaryKey": true,
          "notNull": true,
          "default": "variable_id()"
        },
        "name": {
          "name": "name",
          "type": "text",
          "primaryKey": false,
          "notNull": true
        },
        "value": {
          "name": "value",
          "type": "text",
          "primaryKey": false,
          "notNull": true
        },
        "created_at": {
          "name": "created_at",
          "type": "timestamp",
          "primaryKey": false,
          "notNull": true,
          "default": "now()"
        },
        "updated_at": {
          "name": "updated_at",
          "type": "timestamp",
          "primaryKey": false,
          "notNull": true,
          "default": "now()"
        }
      },
      "indexes": {},
      "foreignKeys": {},
      "compositePrimaryKeys": {},
      "uniqueConstraints": {},
      "policies": {},
      "checkConstraints": {},
      "isRLSEnabled": false
    },
    "public.volumes": {
      "name": "volumes",
      "schema": "",
      "columns": {
        "id": {
          "name": "id",
          "type": "text",
          "primaryKey": true,
          "notNull": true,
          "default": "volume_id()"
        },
        "slug": {
          "name": "slug",
          "type": "text",
          "primaryKey": false,
          "notNull": true
        },
        "size": {
          "name": "size",
          "type": "integer",
          "primaryKey": false,
          "notNull": true
        },
        "size_unit": {
          "name": "size_unit",
          "type": "text",
          "primaryKey": false,
          "notNull": true
        },
        "created_at": {
          "name": "created_at",
          "type": "timestamp",
          "primaryKey": false,
          "notNull": true,
          "default": "now()"
        },
        "updated_at": {
          "name": "updated_at",
          "type": "timestamp",
          "primaryKey": false,
          "notNull": true,
          "default": "now()"
        }
      },
      "indexes": {},
      "foreignKeys": {},
      "compositePrimaryKeys": {},
      "uniqueConstraints": {
        "volumes_slug_unique": {
          "name": "volumes_slug_unique",
          "nullsNotDistinct": false,
          "columns": [
            "slug"
          ]
        }
      },
      "policies": {},
      "checkConstraints": {},
      "isRLSEnabled": false
    }
  },
  "enums": {},
  "schemas": {},
  "sequences": {},
  "roles": {},
  "policies": {},
  "views": {},
  "_meta": {
    "columns": {},
    "schemas": {},
    "tables": {}
  }
}